MANIFEST.in
setup.py
ph_installer.egg-info/PKG-INFO
ph_installer.egg-info/SOURCES.txt
ph_installer.egg-info/dependency_links.txt
ph_installer.egg-info/top_level.txt
photon_installer/EULA.txt
photon_installer/README.txt
photon_installer/__init__.py
photon_installer/action.py
photon_installer/actionresult.py
photon_installer/commandutils.py
photon_installer/confirmwindow.py
photon_installer/custompartition.py
photon_installer/device.py
photon_installer/filedownloader.py
photon_installer/input.json
photon_installer/installer.py
photon_installer/isoInstaller.py
photon_installer/iso_config.py
photon_installer/jsonwrapper.py
photon_installer/ks_config.txt
photon_installer/license.py
photon_installer/linuxselector.py
photon_installer/logger.py
photon_installer/menu.py
photon_installer/mk-setup-grub.sh
photon_installer/netconfig.py
photon_installer/networkmanager.py
photon_installer/ostree-release-repo.conf
photon_installer/ostreeinstaller.py
photon_installer/ostreeserverselector.py
photon_installer/ostreewindowstringreader.py
photon_installer/packageselector.py
photon_installer/partitionpane.py
photon_installer/progressbar.py
photon_installer/readmultext.py
photon_installer/readtext.py
photon_installer/sample_ks.cfg
photon_installer/sample_ui.cfg
photon_installer/selectdisk.py
photon_installer/textpane.py
photon_installer/ui_config.txt
photon_installer/window.py
photon_installer/windowstringreader.py
photon_installer/modules/__init__.py
photon_installer/modules/commons.py
photon_installer/modules/m_locale.py
photon_installer/modules/m_machineid.py
photon_installer/modules/m_postinstall.py
photon_installer/modules/m_updatehostname.py
photon_installer/modules/m_updaterootpassword.py
photon_installer/modules/m_updatesshconfig.py