Metadata-Version: 1.0
Name: ph-installer
Version: 3.2
Summary: Installer code for photon
Home-page: UNKNOWN
Author: UNKNOWN
Author-email: gpiyush@vmware.com
License: UNKNOWN
Platform: UNKNOWN
